Workbook

Sheet Instrucciones
A1: Matriz de requisitos y verificación – CMMS Nutrialimentos Cárnicos S.A.S.
A3: Propósito | B3: Comprobar, requisito por requisito, que el sistema cumple lo definido en el documento del proyecto y en el análisis de vacíos.
A4: Origen | B4: "Doc §" = sección del documento del proyecto. "Análisis" = requisito agregado tras el análisis del documento (vacíos detectados); conviene confirmarlo con los líderes del proceso.
A5: Prioridad | B5: MVP = debe estar en la entrega de 4 semanas (propuesta). Posterior = siguiente fase. Ajustar tras decidir D-14.
A6: Qué llenar | B6: Solo las celdas amarillas de la hoja Matriz: Estado, Responsable, Fecha de verificación y Evidencia. También la columna Decisión de Decisiones pendientes.
A7: Estados | B7: Pendiente · En desarrollo · Cumple · Cumple parcial · No cumple · N/A. Un requisito solo pasa a Cumple cuando TODOS sus criterios se verificaron.
A8: Resumen | B8: La hoja Resumen se calcula sola a partir de la columna Estado. % cumplimiento = Cumple / (Total − N/A).
A9: Decisiones | B9: Los requisitos que mencionan D-xx dependen de una decisión pendiente. Resolverla antes de desarrollar ese requisito.
A11: Ejemplo de fila verificada
A12: ID | B12: Estado | C12: Responsable | D12: Fecha verificación | E12: Evidencia / observaciones
A13: MNT-09 | B13: Cumple | C13: Ana (QA) | D13: 2026-11-18 | E13: Caso: stock 10, OT consume 3 → stock 7. Movimiento #245 vinculado a OT-0031. Captura en carpeta /evidencias/MNT-09.

Sheet Resumen
A1: Resumen de cumplimiento
A2: Se calcula automáticamente desde la hoja Matriz (columna Estado).
A4: Módulo | B4: Total | C4: Cumple | D4: Cumple parcial | E4: No cumple | F4: En desarrollo | G4: Pendiente | H4: N/A | I4: % cumplimiento
A5: General / plataforma | B5: =COUNTIF(Matriz!$B$2:$B$80,A5) -> 2 | C5: =COUNTIFS(Matriz!$B$2:$B$80,$A5,Matriz!$I$2:$I$80,"Cumple") -> 0 | D5: =COUNTIFS(Matriz!$B$2:$B$80,$A5,Matriz!$I$2:$I$80,"Cumple parcial") -> 0 | E5: =COUNTIFS(Matriz!$B$2:$B$80,$A5,Matriz!$I$2:$I$80,"No cumple") -> 0 | F5: =COUNTIFS(Matriz!$B$2:$B$80,$A5,Matriz!$I$2:$I$80,"En desarrollo") -> 0 | G5: =COUNTIFS(Matriz!$B$2:$B$80,$A5,Matriz!$I$2:$I$80,"Pendiente") -> 2 | H5: =COUNTIFS(Matriz!$B$2:$B$80,$A5,Matriz!$I$2:$I$80,"N/A") -> 0 | I5: =IF(B5-H5=0,"-",C5/(B5-H5)) -> 0
A6: Activos y hoja de vida | B6: =COUNTIF(Matriz!$B$2:$B$80,A6) -> 6 | C6: =COUNTIFS(Matriz!$B$2:$B$80,$A6,Matriz!$I$2:$I$80,"Cumple") -> 0 | D6: =COUNTIFS(Matriz!$B$2:$B$80,$A6,Matriz!$I$2:$I$80,"Cumple parcial") -> 0 | E6: =COUNTIFS(Matriz!$B$2:$B$80,$A6,Matriz!$I$2:$I$80,"No cumple") -> 0 | F6: =COUNTIFS(Matriz!$B$2:$B$80,$A6,Matriz!$I$2:$I$80,"En desarrollo") -> 0 | G6: =COUNTIFS(Matriz!$B$2:$B$80,$A6,Matriz!$I$2:$I$80,"Pendiente") -> 6 | H6: =COUNTIFS(Matriz!$B$2:$B$80,$A6,Matriz!$I$2:$I$80,"N/A") -> 0 | I6: =IF(B6-H6=0,"-",C6/(B6-H6)) -> 0
A7: Calidad HACCP/BPM y temperaturas | B7: =COUNTIF(Matriz!$B$2:$B$80,A7) -> 7 | C7: =COUNTIFS(Matriz!$B$2:$B$80,$A7,Matriz!$I$2:$I$80,"Cumple") -> 0 | D7: =COUNTIFS(Matriz!$B$2:$B$80,$A7,Matriz!$I$2:$I$80,"Cumple parcial") -> 0 | E7: =COUNTIFS(Matriz!$B$2:$B$80,$A7,Matriz!$I$2:$I$80,"No cumple") -> 0 | F7: =COUNTIFS(Matriz!$B$2:$B$80,$A7,Matriz!$I$2:$I$80,"En desarrollo") -> 0 | G7: =COUNTIFS(Matriz!$B$2:$B$80,$A7,Matriz!$I$2:$I$80,"Pendiente") -> 7 | H7: =COUNTIFS(Matriz!$B$2:$B$80,$A7,Matriz!$I$2:$I$80,"N/A") -> 0 | I7: =IF(B7-H7=0,"-",C7/(B7-H7)) -> 0
A8: Mantenimiento (OT) | B8: =COUNTIF(Matriz!$B$2:$B$80,A8) -> 11 | C8: =COUNTIFS(Matriz!$B$2:$B$80,$A8,Matriz!$I$2:$I$80,"Cumple") -> 0 | D8: =COUNTIFS(Matriz!$B$2:$B$80,$A8,Matriz!$I$2:$I$80,"Cumple parcial") -> 0 | E8: =COUNTIFS(Matriz!$B$2:$B$80,$A8,Matriz!$I$2:$I$80,"No cumple") -> 0 | F8: =COUNTIFS(Matriz!$B$2:$B$80,$A8,Matriz!$I$2:$I$80,"En desarrollo") -> 0 | G8: =COUNTIFS(Matriz!$B$2:$B$80,$A8,Matriz!$I$2:$I$80,"Pendiente") -> 11 | H8: =COUNTIFS(Matriz!$B$2:$B$80,$A8,Matriz!$I$2:$I$80,"N/A") -> 0 | I8: =IF(B8-H8=0,"-",C8/(B8-H8)) -> 0
A9: Funcionamiento offline | B9: =COUNTIF(Matriz!$B$2:$B$80,A9) -> 8 | C9: =COUNTIFS(Matriz!$B$2:$B$80,$A9,Matriz!$I$2:$I$80,"Cumple") -> 0 | D9: =COUNTIFS(Matriz!$B$2:$B$80,$A9,Matriz!$I$2:$I$80,"Cumple parcial") -> 0 | E9: =COUNTIFS(Matriz!$B$2:$B$80,$A9,Matriz!$I$2:$I$80,"No cumple") -> 0 | F9: =COUNTIFS(Matriz!$B$2:$B$80,$A9,Matriz!$I$2:$I$80,"En desarrollo") -> 0 | G9: =COUNTIFS(Matriz!$B$2:$B$80,$A9,Matriz!$I$2:$I$80,"Pendiente") -> 8 | H9: =COUNTIFS(Matriz!$B$2:$B$80,$A9,Matriz!$I$2:$I$80,"N/A") -> 0 | I9: =IF(B9-H9=0,"-",C9/(B9-H9)) -> 0
A10: Inventario de repuestos | B10: =COUNTIF(Matriz!$B$2:$B$80,A10) -> 9 | C10: =COUNTIFS(Matriz!$B$2:$B$80,$A10,Matriz!$I$2:$I$80,"Cumple") -> 0 | D10: =COUNTIFS(Matriz!$B$2:$B$80,$A10,Matriz!$I$2:$I$80,"Cumple parcial") -> 0 | E10: =COUNTIFS(Matriz!$B$2:$B$80,$A10,Matriz!$I$2:$I$80,"No cumple") -> 0 | F10: =COUNTIFS(Matriz!$B$2:$B$80,$A10,Matriz!$I$2:$I$80,"En desarrollo") -> 0 | G10: =COUNTIFS(Matriz!$B$2:$B$80,$A10,Matriz!$I$2:$I$80,"Pendiente") -> 9 | H10: =COUNTIFS(Matriz!$B$2:$B$80,$A10,Matriz!$I$2:$I$80,"N/A") -> 0 | I10: =IF(B10-H10=0,"-",C10/(B10-H10)) -> 0
A11: Solicitudes de compra | B11: =COUNTIF(Matriz!$B$2:$B$80,A11) -> 9 | C11: =COUNTIFS(Matriz!$B$2:$B$80,$A11,Matriz!$I$2:$I$80,"Cumple") -> 0 | D11: =COUNTIFS(Matriz!$B$2:$B$80,$A11,Matriz!$I$2:$I$80,"Cumple parcial") -> 0 | E11: =COUNTIFS(Matriz!$B$2:$B$80,$A11,Matriz!$I$2:$I$80,"No cumple") -> 0 | F11: =COUNTIFS(Matriz!$B$2:$B$80,$A11,Matriz!$I$2:$I$80,"En desarrollo") -> 0 | G11: =COUNTIFS(Matriz!$B$2:$B$80,$A11,Matriz!$I$2:$I$80,"Pendiente") -> 9 | H11: =COUNTIFS(Matriz!$B$2:$B$80,$A11,Matriz!$I$2:$I$80,"N/A") -> 0 | I11: =IF(B11-H11=0,"-",C11/(B11-H11)) -> 0
A12: Indicadores y reportes | B12: =COUNTIF(Matriz!$B$2:$B$80,A12) -> 7 | C12: =COUNTIFS(Matriz!$B$2:$B$80,$A12,Matriz!$I$2:$I$80,"Cumple") -> 0 | D12: =COUNTIFS(Matriz!$B$2:$B$80,$A12,Matriz!$I$2:$I$80,"Cumple parcial") -> 0 | E12: =COUNTIFS(Matriz!$B$2:$B$80,$A12,Matriz!$I$2:$I$80,"No cumple") -> 0 | F12: =COUNTIFS(Matriz!$B$2:$B$80,$A12,Matriz!$I$2:$I$80,"En desarrollo") -> 0 | G12: =COUNTIFS(Matriz!$B$2:$B$80,$A12,Matriz!$I$2:$I$80,"Pendiente") -> 7 | H12: =COUNTIFS(Matriz!$B$2:$B$80,$A12,Matriz!$I$2:$I$80,"N/A") -> 0 | I12: =IF(B12-H12=0,"-",C12/(B12-H12)) -> 0
A13: Roles, acceso y seguridad | B13: =COUNTIF(Matriz!$B$2:$B$80,A13) -> 6 | C13: =COUNTIFS(Matriz!$B$2:$B$80,$A13,Matriz!$I$2:$I$80,"Cumple") -> 0 | D13: =COUNTIFS(Matriz!$B$2:$B$80,$A13,Matriz!$I$2:$I$80,"Cumple parcial") -> 0 | E13: =COUNTIFS(Matriz!$B$2:$B$80,$A13,Matriz!$I$2:$I$80,"No cumple") -> 0 | F13: =COUNTIFS(Matriz!$B$2:$B$80,$A13,Matriz!$I$2:$I$80,"En desarrollo") -> 0 | G13: =COUNTIFS(Matriz!$B$2:$B$80,$A13,Matriz!$I$2:$I$80,"Pendiente") -> 6 | H13: =COUNTIFS(Matriz!$B$2:$B$80,$A13,Matriz!$I$2:$I$80,"N/A") -> 0 | I13: =IF(B13-H13=0,"-",C13/(B13-H13)) -> 0
A14: Notificaciones | B14: =COUNTIF(Matriz!$B$2:$B$80,A14) -> 2 | C14: =COUNTIFS(Matriz!$B$2:$B$80,$A14,Matriz!$I$2:$I$80,"Cumple") -> 0 | D14: =COUNTIFS(Matriz!$B$2:$B$80,$A14,Matriz!$I$2:$I$80,"Cumple parcial") -> 0 | E14: =COUNTIFS(Matriz!$B$2:$B$80,$A14,Matriz!$I$2:$I$80,"No cumple") -> 0 | F14: =COUNTIFS(Matriz!$B$2:$B$80,$A14,Matriz!$I$2:$I$80,"En desarrollo") -> 0 | G14: =COUNTIFS(Matriz!$B$2:$B$80,$A14,Matriz!$I$2:$I$80,"Pendiente") -> 2 | H14: =COUNTIFS(Matriz!$B$2:$B$80,$A14,Matriz!$I$2:$I$80,"N/A") -> 0 | I14: =IF(B14-H14=0,"-",C14/(B14-H14)) -> 0
A15: No funcionales | B15: =COUNTIF(Matriz!$B$2:$B$80,A15) -> 4 | C15: =COUNTIFS(Matriz!$B$2:$B$80,$A15,Matriz!$I$2:$I$80,"Cumple") -> 0 | D15: =COUNTIFS(Matriz!$B$2:$B$80,$A15,Matriz!$I$2:$I$80,"Cumple parcial") -> 0 | E15: =COUNTIFS(Matriz!$B$2:$B$80,$A15,Matriz!$I$2:$I$80,"No cumple") -> 0 | F15: =COUNTIFS(Matriz!$B$2:$B$80,$A15,Matriz!$I$2:$I$80,"En desarrollo") -> 0 | G15: =COUNTIFS(Matriz!$B$2:$B$80,$A15,Matriz!$I$2:$I$80,"Pendiente") -> 4 | H15: =COUNTIFS(Matriz!$B$2:$B$80,$A15,Matriz!$I$2:$I$80,"N/A") -> 0 | I15: =IF(B15-H15=0,"-",C15/(B15-H15)) -> 0
A16: Datos e integración SAP | B16: =COUNTIF(Matriz!$B$2:$B$80,A16) -> 3 | C16: =COUNTIFS(Matriz!$B$2:$B$80,$A16,Matriz!$I$2:$I$80,"Cumple") -> 0 | D16: =COUNTIFS(Matriz!$B$2:$B$80,$A16,Matriz!$I$2:$I$80,"Cumple parcial") -> 0 | E16: =COUNTIFS(Matriz!$B$2:$B$80,$A16,Matriz!$I$2:$I$80,"No cumple") -> 0 | F16: =COUNTIFS(Matriz!$B$2:$B$80,$A16,Matriz!$I$2:$I$80,"En desarrollo") -> 0 | G16: =COUNTIFS(Matriz!$B$2:$B$80,$A16,Matriz!$I$2:$I$80,"Pendiente") -> 3 | H16: =COUNTIFS(Matriz!$B$2:$B$80,$A16,Matriz!$I$2:$I$80,"N/A") -> 0 | I16: =IF(B16-H16=0,"-",C16/(B16-H16)) -> 0
A17: Implementación y entrega | B17: =COUNTIF(Matriz!$B$2:$B$80,A17) -> 5 | C17: =COUNTIFS(Matriz!$B$2:$B$80,$A17,Matriz!$I$2:$I$80,"Cumple") -> 0 | D17: =COUNTIFS(Matriz!$B$2:$B$80,$A17,Matriz!$I$2:$I$80,"Cumple parcial") -> 0 | E17: =COUNTIFS(Matriz!$B$2:$B$80,$A17,Matriz!$I$2:$I$80,"No cumple") -> 0 | F17: =COUNTIFS(Matriz!$B$2:$B$80,$A17,Matriz!$I$2:$I$80,"En desarrollo") -> 0 | G17: =COUNTIFS(Matriz!$B$2:$B$80,$A17,Matriz!$I$2:$I$80,"Pendiente") -> 5 | H17: =COUNTIFS(Matriz!$B$2:$B$80,$A17,Matriz!$I$2:$I$80,"N/A") -> 0 | I17: =IF(B17-H17=0,"-",C17/(B17-H17)) -> 0
A18: TOTAL | B18: =SUM(B5:B17) -> 79 | C18: =SUM(C5:C17) -> 0 | D18: =SUM(D5:D17) -> 0 | E18: =SUM(E5:E17) -> 0 | F18: =SUM(F5:F17) -> 0 | G18: =SUM(G5:G17) -> 79 | H18: =SUM(H5:H17) -> 0 | I18: =IF(B18-H18=0,"-",C18/(B18-H18)) -> 0
A19: Solo requisitos MVP | B19: =COUNTIF(Matriz!$E$2:$E$80,"MVP") -> 66 | C19: =COUNTIFS(Matriz!$E$2:$E$80,"MVP",Matriz!$I$2:$I$80,"Cumple") -> 0 | D19: =COUNTIFS(Matriz!$E$2:$E$80,"MVP",Matriz!$I$2:$I$80,"Cumple parcial") -> 0 | E19: =COUNTIFS(Matriz!$E$2:$E$80,"MVP",Matriz!$I$2:$I$80,"No cumple") -> 0 | F19: =COUNTIFS(Matriz!$E$2:$E$80,"MVP",Matriz!$I$2:$I$80,"En desarrollo") -> 0 | G19: =COUNTIFS(Matriz!$E$2:$E$80,"MVP",Matriz!$I$2:$I$80,"Pendiente") -> 66 | H19: =COUNTIFS(Matriz!$E$2:$E$80,"MVP",Matriz!$I$2:$I$80,"N/A") -> 0 | I19: =IF(B19-H19=0,"-",C19/(B19-H19)) -> 0
A21: Decisiones pendientes sin resolver: | B21: =COUNTBLANK('Decisiones pendientes'!F2:F16) -> 15

Sheet Matriz
A1: ID | B1: Módulo | C1: Requisito | D1: Origen | E1: Prioridad | F1: Rol(es) | G1: Criterios de aceptación | H1: Método de verificación | I1: Estado | J1: Responsable | K1: Fecha verificación | L1: Evidencia / observaciones
A2: GEN-01 | B2: General / plataforma | C2: La aplicación funciona en celular, tablet y computador. | D2: Doc §1, §3 | E2: MVP | F2: Todos | G2: 1. Usable en Android (Chrome), iOS (Safari) y Windows (Chrome/Edge). 2. Sin desplazamiento horizontal a 360 px de ancho. 3. Botones táctiles de al menos 44 px (uso con guantes). | H2: Prueba manual en los 3 tipos de dispositivo | I2: Pendiente
A3: GEN-02 | B3: General / plataforma | C3: La interfaz está en español y es comprensible para personal de planta. | D3: Doc §1 | E3: MVP | F3: Todos | G3: 1. Todos los textos y mensajes de error en español. 2. Un operario nuevo completa un reporte de falla sin ayuda tras una demostración de 5 min. | H3: Prueba de usabilidad con 3 operarios | I3: Pendiente
A4: ACT-01 | B4: Activos y hoja de vida | C4: Crear y editar la ficha técnica de cada máquina. | D4: Doc §2A | E4: MVP | F4: Administrador | G4: 1. Campos: código único, nombre, modelo, fabricante, área/ubicación, fecha de compra, fin de garantía, estado. 2. No permite códigos duplicados. 3. Valida campos obligatorios. 4. Solo el Administrador puede crear o editar. | H4: Prueba funcional + prueba de permisos con otros roles | I4: Pendiente
A5: ACT-02 | B5: Activos y hoja de vida | C5: Adjuntar manuales y documentos a la ficha de la máquina. | D5: Doc §2A | E5: MVP | F5: Administrador; consulta: todos | G5: 1. Acepta PDF, JPG y PNG hasta el tamaño máximo definido. 2. Se pueden abrir desde el celular. 3. Registra quién y cuándo subió cada archivo. | H5: Prueba funcional en celular y PC | I5: Pendiente
A6: ACT-03 | B6: Activos y hoja de vida | C6: Hoja de vida: historial cronológico de cada máquina. | D6: Doc §1, §2A | E6: MVP | F6: Todos (consulta) | G6: 1. Muestra fallas, mantenimientos, repuestos consumidos y costos. 2. Al cerrar una OT aparece de inmediato en el historial. 3. Filtrable por rango de fechas y tipo (preventivo/correctivo). | H6: Prueba funcional con OT de prueba | I6: Pendiente
A7: ACT-04 | B7: Activos y hoja de vida | C7: Costo acumulado por máquina (LCC) calculado automáticamente. | D7: Doc §2A; Análisis §1 | E7: MVP | F7: Administrador, Dirección | G7: 1. Suma repuestos + mano de obra + servicios externos (según D-03). 2. Con un caso de prueba de al menos 3 OT cerradas, el valor coincide con el cálculo manual. 3. Se actualiza al cerrar cada OT. 4. Muestra desglose por tipo de costo. | H7: Caso de prueba con cálculo manual en Excel | I7: Pendiente
A8: ACT-05 | B8: Activos y hoja de vida | C8: Alerta de garantía próxima a vencer. | D8: Análisis | E8: Posterior | F8: Administrador | G8: 1. Aviso X días antes del fin de garantía (X configurable). | H8: Prueba con fecha simulada | I8: Pendiente
A9: ACT-06 | B9: Activos y hoja de vida | C9: Código QR por máquina que abre su ficha o el reporte de falla. | D9: Análisis | E9: Posterior | F9: Todos | G9: 1. Se genera e imprime el QR de cada máquina. 2. Al escanearlo con el celular abre la máquina correcta. | H9: Prueba en planta con 3 máquinas | I9: Pendiente
A10: CAL-01 | B10: Calidad HACCP/BPM y temperaturas | C10: Registro de temperaturas (congelación/cocción) por equipo. | D10: Doc §1, §2A | E10: MVP | F10: Operario | G10: 1. Guarda equipo, valor en °C, fecha/hora del dispositivo y del servidor, y usuario. 2. Valor numérico validado (no acepta texto). | H10: Prueba funcional | I10: Pendiente
A11: CAL-02 | B11: Calidad HACCP/BPM y temperaturas | C11: Límites críticos configurables por equipo con alerta fuera de rango. | D11: Análisis §3 | E11: MVP | F11: Administrador (config.); Operario | G11: 1. Cada equipo tiene mínimo y máximo configurables. 2. Un valor fuera de rango se marca en rojo y notifica al responsable de calidad/mantenimiento. | H11: Prueba con valores dentro y fuera de rango | I11: Pendiente
A12: CAL-03 | B12: Calidad HACCP/BPM y temperaturas | C12: Acción correctiva obligatoria ante una desviación. | D12: Análisis §3 | E12: MVP | F12: Operario | G12: 1. No permite guardar un registro fuera de rango sin describir la acción correctiva. 2. Queda el responsable y la hora de la acción. | H12: Prueba funcional | I12: Pendiente
A13: CAL-04 | B13: Calidad HACCP/BPM y temperaturas | C13: Checklists pre-operacionales y de aseo (HACCP/BPM) configurables. | D13: Doc §1, §2A | E13: MVP | F13: Administrador (plantillas); Operario | G13: 1. El Administrador crea plantillas por equipo/área con ítems Sí/No, numérico, texto y foto. 2. El operario diligencia y envía. 3. Queda registrado usuario, fecha y hora. 4. Ítems no conformes quedan resaltados. | H13: Prueba funcional con una plantilla real de calidad | I13: Pendiente
... A80: IMP-05 | B80: Implementación y entrega | C80: Salida a operación con plan de soporte. | D80: Doc §5; Análisis §5 | E80: MVP | F80: Sistemas | G80: 1. Fecha de salida definida. 2. Canal de soporte y responsable durante las primeras semanas. 3. Procedimiento para reportar errores. | H80: Revisión documental | I80: Pendiente

Sheet Decisiones pendientes
A1: ID | B1: Tema | C1: Pregunta a resolver | D1: Requisitos afectados | E1: Quién decide | F1: Decisión tomada | G1: Fecha
A2: D-01 | B2: Conflictos offline | C2: ¿Qué pasa si dos personas modifican la misma OT sin conexión? (ej. gana el primero en sincronizar y el segundo recibe aviso) | D2: OFF-05 | E2: Equipo dev + Carlos
A3: D-02 | B3: Stock negativo | C3: Si se sincroniza un consumo offline y no hay stock suficiente: ¿se permite negativo con alerta, o se bloquea y se ajusta? | D3: OFF-06, INV-03 | E3: Carlos, Yineth
A4: D-03 | B4: Alcance del LCC | C4: ¿El costo por máquina incluye mano de obra y servicios externos? ¿Qué tarifa por hora se usa para los técnicos? | D4: ACT-04, MNT-10 | E4: Dirección
A5: D-04 | B5: Costeo de inventario | C5: Método de costeo de repuestos (promedio ponderado, último costo…) y consistencia con contabilidad/SAP. | D5: INV-08, KPI-05 | E5: Dirección + Contabilidad
A6: D-05 | B6: Definición de KPIs | C6: Fórmulas, metas, período de cálculo y de dónde sale el tiempo planificado de producción. | D6: KPI-01 a KPI-07 | E6: Dirección
A7: D-06 | B7: Límites críticos | C7: Rango de temperatura por equipo y frecuencia de registro exigida. | D7: CAL-02, CAL-07 | E7: Calidad
A8: D-07 | B8: Requisitos normativos | C8: Requisitos de los registros HACCP/BPM según la normativa aplicable y el auditor (retención, firma, formato de exportación). | D8: CAL-05, CAL-06 | E8: Calidad
A9: D-08 | B9: Cambio de autorizador | C9: Al cambiar de autorizador, ¿las solicitudes pendientes pasan al nuevo? ¿Habrá suplente o montos con doble aprobación? | D9: COM-04, COM-09 | E9: Dirección
A10: D-09 | B10: Rechazo de compras | C10: Estado de la OT tras un rechazo (esperando repuesto, reprogramada, cancelada) y quién decide. | D10: COM-06 | E10: Carlos, Juan Camilo
A11: D-10 | B11: Canal de notificaciones | C11: Push, correo, WhatsApp o solo dentro de la app. Considerar limitaciones de iPhone. | D11: NOT-01 | E11: Dirección + Sistemas
A12: D-11 | B12: Login en planta | C12: Método de ingreso en planta (PIN, QR personal, usuario/contraseña) y tiempo de cierre por inactividad. | D12: SEG-02 | E12: Sistemas + Carlos
A13: D-12 | B13: Infraestructura | C13: Servidor propio o nube, política de respaldos y retención. | D13: NFR-01, NFR-03 | E13: Sistemas
... A16: D-15 | B16: Rol Técnico | C16: Confirmar rol Técnico separado del Operario y quién cierra las OT. | D16: SEG-03, MNT-03 | E16: Carlos
